global_apbd_logging/__init__.py
global_apbd_logging/nabire_logging.py
global_apbd_logging-1.0.1.dist-info/LICENSE
global_apbd_logging-1.0.1.dist-info/METADATA
global_apbd_logging-1.0.1.dist-info/WHEEL
global_apbd_logging-1.0.1.dist-info/entry_points.txt
global_apbd_logging-1.0.1.dist-info/top_level.txt
global_apbd_logging-1.0.1.dist-info/RECORD
