Metadata-Version: 2.1
Name: global-apbd-logging
Version: 1.0.1
Summary: A Python package to get log of apbd.
Home-page: https://github.com/adityayudhi/global_apbd_logging
Author: Aditya Yudhi Hanafi
Author-email: adityayudhi10@gmail.com
License: MIT
Platform: UNKNOWN
Classifier: License :: OSI Approved :: MIT License
Classifier: Programming Language :: Python :: 3
Classifier: Programming Language :: Python :: 3.7
Requires-Dist: httpagentparser
Requires-Dist: get-mac
Requires-Dist: requests
